generic_lexer/__init__.py
generic_lexer-1.1.1.dist-info/LICENSE
generic_lexer-1.1.1.dist-info/METADATA
generic_lexer-1.1.1.dist-info/WHEEL
generic_lexer-1.1.1.dist-info/top_level.txt
generic_lexer-1.1.1.dist-info/zip-safe
generic_lexer-1.1.1.dist-info/RECORD
