Metadata-Version: 2.1
Name: generic-lexer
Version: 1.1.1
Summary: A generic pattern-based Lexer/tokenizer tool.
Home-page: https://github.com/Cerberus1746/generic_lexer/
Author: Eli Bendersky
Author-email: eliben@gmail.com
Maintainer: Leandro Benedet Garcia
Maintainer-email: cerberus1746@gmail.com
License: The Unlicense
Project-URL: Repository, https://github.com/Cerberus1746/generic_lexer
Project-URL: Bug Tracker, https://github.com/Cerberus1746/generic_lexer/issues
Project-URL: Documentation, https://cerberus1746.github.io/generic_lexer/
Keywords: parser,lexer,tokenizer
Platform: UNKNOWN
Classifier: Programming Language :: Python
Classifier: Programming Language :: Python :: Implementation :: PyPy
Classifier: Programming Language :: Python :: Implementation :: CPython
Classifier: Programming Language :: Python :: 3
Classifier: Programming Language :: Python :: 3 :: Only
Classifier: Programming Language :: Python :: 3.5
Classifier: Programming Language :: Python :: 3.6
Classifier: Programming Language :: Python :: 3.7
Classifier: Programming Language :: Python :: 3.8
Classifier: Programming Language :: Python :: 3.9
Classifier: License :: OSI Approved :: The Unlicense (Unlicense)
Classifier: Intended Audience :: Developers
Classifier: Development Status :: 5 - Production/Stable
Classifier: Topic :: Software Development
Classifier: Topic :: Software Development :: Interpreters
Classifier: Topic :: Text Processing
Requires-Python: >=3.5
Provides-Extra: docs
Requires-Dist: sphinx-autodoc-typehints ; extra == 'docs'
Provides-Extra: tests
Requires-Dist: sphinx-autodoc-typehints ; extra == 'tests'
Requires-Dist: tox ; extra == 'tests'
